sparse_pendulum/__init__.py
sparse_pendulum/envs/__init__.py
sparse_pendulum/envs/sparse_pendulum.py
sparse_pendulum-0.0.6.dist-info/METADATA
sparse_pendulum-0.0.6.dist-info/WHEEL
sparse_pendulum-0.0.6.dist-info/top_level.txt
sparse_pendulum-0.0.6.dist-info/RECORD
