Metadata-Version: 2.1
Name: sparse-pendulum
Version: 0.0.6
Summary: Open AI gym Pendulum Env with sparse rewards
Home-page: UNKNOWN
Author: Christoper Glenn Wulur
Author-email: christoper.glennwu@gmail.com
License: UNKNOWN
Platform: UNKNOWN
Requires-Dist: gym
